cherv/__init__.py
cherv/__main__.py
cherv/cherv.py
Cherv-0.5.2.dist-info/LICENSE
Cherv-0.5.2.dist-info/METADATA
Cherv-0.5.2.dist-info/WHEEL
Cherv-0.5.2.dist-info/entry_points.txt
Cherv-0.5.2.dist-info/top_level.txt
Cherv-0.5.2.dist-info/RECORD
